pyflink/__init__.py
cp_pyflink_libraries-0.0.0.dist-info/METADATA
cp_pyflink_libraries-0.0.0.dist-info/WHEEL
cp_pyflink_libraries-0.0.0.dist-info/top_level.txt
cp_pyflink_libraries-0.0.0.dist-info/RECORD
