Metadata-Version: 2.4
Name: cp-pyflink-libraries
Version: 0.0.0
Summary: Flink libraries for PyFlink on Confluent Platform
License-Expression: Apache-2.0
Classifier: Programming Language :: Python :: 3
Classifier: Operating System :: OS Independent
Requires-Python: >=3.9
